zd_tools/__init__.py
zd_tools/bulk_actions_tickets.py
zd_tools/bulk_actions_users.py
zd_tools/merge_accounts.py
zd_tools/modify_tickets.py
zd_tools/modify_users.py
zd_tools/update_organization.py
zd_tools/zd_requests.py
umb_zd_tools-0.0.1.dist-info/LICENSE
umb_zd_tools-0.0.1.dist-info/METADATA
umb_zd_tools-0.0.1.dist-info/WHEEL
umb_zd_tools-0.0.1.dist-info/top_level.txt
umb_zd_tools-0.0.1.dist-info/RECORD
