Metadata-Version: 2.1
Name: umb-zd-tools
Version: 0.0.1
Summary: Common HTTP calls for Umbrella Zendesk
Home-page: https://github.office.opendns.com/CustomerSuccess/zendesk_api_wrapper.git
Author: Geoff Gallinger (ggalling)
Author-email: ggalling@cisco.com
License: UNKNOWN
Platform: UNKNOWN
Classifier: Programming Language :: Python :: 3
Classifier: License :: OSI Approved :: MIT License
Classifier: Operating System :: OS Independent
Requires-Python: >=3.8
